sakura/__init__.py
sakura/providers/__init__.py
sakura/providers/fastapi_provider/__init__.py
sakura/providers/fastapi_provider/provider.py
sakura/providers/fastapi_provider/test_provider.py
sakura_fastapi_provider-0.1.0.dist-info/METADATA
sakura_fastapi_provider-0.1.0.dist-info/WHEEL
sakura_fastapi_provider-0.1.0.dist-info/RECORD
