Metadata-Version: 2.1
Name: sakura-fastapi-provider
Version: 0.1.0
Summary: 
Requires-Python: >=3.9,<4.0
Classifier: Programming Language :: Python :: 3
Classifier: Programming Language :: Python :: 3.9
Classifier: Programming Language :: Python :: 3.10
Classifier: Programming Language :: Python :: 3.11
Requires-Dist: fastapi (==0.78.0)
Requires-Dist: sakura-core (>=0.1.1,<0.2.0)
Requires-Dist: uvicorn (>=0.23.1,<0.24.0)
